meganote_python_editor_extension-0.1.1.data/data/share/jupyter/labextensions/meganote-python-editor-extension/install.json
meganote_python_editor_extension-0.1.1.data/data/share/jupyter/labextensions/meganote-python-editor-extension/package.json
meganote_python_editor_extension-0.1.1.data/data/share/jupyter/labextensions/meganote-python-editor-extension/static/260.d1e96beb067a53b6c0ca.js
meganote_python_editor_extension-0.1.1.data/data/share/jupyter/labextensions/meganote-python-editor-extension/static/747.4d21d7beb498d859bfb0.js
meganote_python_editor_extension-0.1.1.data/data/share/jupyter/labextensions/meganote-python-editor-extension/static/remoteEntry.ce2bacac78a9d2a26686.js
meganote_python_editor_extension-0.1.1.data/data/share/jupyter/labextensions/meganote-python-editor-extension/static/style.js
meganote_python_editor_extension-0.1.1.data/data/share/jupyter/labextensions/meganote-python-editor-extension/static/third-party-licenses.json
python_editor/__init__.py
python_editor/_version.py
python_editor/labextension/package.json
python_editor/labextension/static/260.d1e96beb067a53b6c0ca.js
python_editor/labextension/static/747.4d21d7beb498d859bfb0.js
python_editor/labextension/static/remoteEntry.ce2bacac78a9d2a26686.js
python_editor/labextension/static/style.js
python_editor/labextension/static/third-party-licenses.json
meganote_python_editor_extension-0.1.1.dist-info/LICENSE
meganote_python_editor_extension-0.1.1.dist-info/METADATA
meganote_python_editor_extension-0.1.1.dist-info/WHEEL
meganote_python_editor_extension-0.1.1.dist-info/top_level.txt
meganote_python_editor_extension-0.1.1.dist-info/RECORD
